lyn/__init__.py
lyn/codes.py
lyn/lyn.py
lyn/registers.py
lyn-0.0.6.dist-info/DESCRIPTION.rst
lyn-0.0.6.dist-info/METADATA
lyn-0.0.6.dist-info/metadata.json
lyn-0.0.6.dist-info/RECORD
lyn-0.0.6.dist-info/top_level.txt
lyn-0.0.6.dist-info/WHEEL
lyn-0.0.6.dist-info/zip-safe
