Metadata-Version: 2.0
Name: lyn
Version: 0.0.6
Summary: Python bindings for GNU Lightning JIT
Home-page: https://github.com/cslarsen/lyn
Author: Christian Stigen Larsen
Author-email: csl@csl.name
License: https://www.gnu.org/licenses/lgpl-2.1.html
Download-URL: https://github.com/cslarsen/lyn/tarball/v0.0.6
Keywords: jit,compilation,bytecode,assembly,just-in-time,compiler,machine code,native code,speed
Platform: unix
Platform: linux
Platform: osx
Platform: cygwin
Platform: win32
Classifier: Development Status :: 3 - Alpha
Classifier: Natural Language :: English
Requires-Dist: enum34
Requires-Dist: six
